async_sabnzbd/__init__.py
async_sabnzbd/sabnzbd.py
async_sabnzbd-0.1.0.dist-info/METADATA
async_sabnzbd-0.1.0.dist-info/WHEEL
async_sabnzbd-0.1.0.dist-info/RECORD
